nova_rerun_bridge/__init__.py
nova_rerun_bridge/blueprint.py
nova_rerun_bridge/collision_scene.py
nova_rerun_bridge/colors.py
nova_rerun_bridge/consts.py
nova_rerun_bridge/conversion_helpers.py
nova_rerun_bridge/dh_robot.py
nova_rerun_bridge/examples/02_plan_and_execute.py
nova_rerun_bridge/examples/03_move_and_set_ios.py
nova_rerun_bridge/examples/04_move_multiple_robots.py
nova_rerun_bridge/examples/05_selection_motion_group_activation.py
nova_rerun_bridge/examples/08_stream_robot.py
nova_rerun_bridge/examples/09_plan_and_execute_failed.py
nova_rerun_bridge/examples/10_import_ply.py
nova_rerun_bridge/examples/11_standard_skill.py
nova_rerun_bridge/examples/12_external_axis.py
nova_rerun_bridge/examples/13_collision_free_p2p.py
nova_rerun_bridge/examples/standard_skill.ws
nova_rerun_bridge/examples/timing_mode.py
nova_rerun_bridge/examples/yaskawa-ar1440-16-mounting.json
nova_rerun_bridge/examples/yaskawa-ar1440-with-external-axis.json
nova_rerun_bridge/helper_scripts/README.md
nova_rerun_bridge/helper_scripts/download_models.py
nova_rerun_bridge/helper_scripts/plan_with_collisions.py
nova_rerun_bridge/helper_scripts/unpack_models.sh
nova_rerun_bridge/hull_visualizer.py
nova_rerun_bridge/motion_storage.py
nova_rerun_bridge/nova_reun_bridge.py
nova_rerun_bridge/polling/populate.py
nova_rerun_bridge/robot_visualizer.py
nova_rerun_bridge/stream_state.py
nova_rerun_bridge/trajectory.py
nova_rerun_bridge-0.31.0.dist-info/LICENSE
nova_rerun_bridge-0.31.0.dist-info/METADATA
nova_rerun_bridge-0.31.0.dist-info/WHEEL
nova_rerun_bridge-0.31.0.dist-info/entry_points.txt
nova_rerun_bridge-0.31.0.dist-info/RECORD
