Metadata-Version: 2.3
Name: nova-rerun-bridge
Version: 0.31.0
Summary: Visualizes the state of your nova instance inside of [rerun.io](https://rerun.io). This is intended to be used alongside the [nova python lib](https://github.com/wandelbotsgmbh/wandelbots-nova).
Author: Wandelbots GmbH
Requires-Python: >=3.10,<4.0
Classifier: Programming Language :: Python :: 3
Classifier: Programming Language :: Python :: 3.10
Classifier: Programming Language :: Python :: 3.11
Classifier: Programming Language :: Python :: 3.12
Classifier: Programming Language :: Python :: 3.13
Requires-Dist: APScheduler (>=3.11.0,<4.0.0)
Requires-Dist: python-decouple (>=3.8,<4.0)
Requires-Dist: requests (>=2.32.3,<3.0.0)
Requires-Dist: rerun-sdk (>=0.21.0,<0.22.0)
Requires-Dist: scipy (>=1.14.1,<2.0.0)
Requires-Dist: trimesh (>=4.5.3,<5.0.0)
Requires-Dist: wandelbots-nova (>=0.18.0)
